lbcollage/__init__.py
lbcollage/brainzrequest.py
lbcollage/constants.py
lbcollage/imageprocessing.py
lbcollage/preferences.py
lbcollage-0.1.2.dist-info/METADATA
lbcollage-0.1.2.dist-info/WHEEL
lbcollage-0.1.2.dist-info/entry_points.txt
lbcollage-0.1.2.dist-info/top_level.txt
lbcollage-0.1.2.dist-info/RECORD
