Metadata-Version: 2.1
Name: lbcollage
Version: 0.1.2
Summary: Create a collage of album art from your ListenBrainz listening history
Author-email: Thom Cameron <thomcameron98@protonmail.com>
Requires-Dist: argparse
Requires-Dist: pylistenbrainz
Requires-Dist: musicbrainzngs
Requires-Dist: pillow
